{
  "context": {
    "domain": "ONDC:RET12",
    "country": "IND",
    "city": "std:0124",
    "core_version": "1.2.5",
    "action": "on_select",
    "transaction_id": "28a5773c-9029-4f1b-abcb-e8a1e9fb85eb",
    "message_id": "ffc48e7d-315e-42e6-83bd-f50df1c721ef",
    "timestamp": "2025-04-28T10:17:30.869Z",
    "bap_uri": "https://ondc.sequelstring.com/buyer/protocol",
    "bap_id": "ondc.sequelstring.com/buyer/protocol",
    "bpp_id": "ondc.sequelstring.com/seller/protocol",
    "bpp_uri": "https://ondc.sequelstring.com/protocol"
  },
  "message": {
    "order": {
      "fulfillments": [
        {
          "id": "4f71be37-57bb-439a-b803-e1133d6105d5",
          "type": "Delivery",
          "@ondc/org/provider_name": "Pramaan Store 1",
          "tracking": true,
          "@ondc/org/category": "Standard Delivery",
          "@ondc/org/TAT": "PT24H",
          "state": {
            "descriptor": {
              "code": "Serviceable"
            }
          }
        },
        {
          "id": "2490fae2-690e-4694-bedc-50aac1ed1d85",
          "type": "Self-Pickup",
          "@ondc/org/provider_name": "Pramaan Store 1",
          "tracking": false,
          "@ondc/org/category": "Takeaway",
          "@ondc/org/TAT": "PT24H",
          "state": {
            "descriptor": {
              "code": "Serviceable"
            }
          }
        },
        {
          "id": "d0499d73-d43e-4957-b3a2-a3e306db0d1e",
          "type": "Buyer-Delivery",
          "@ondc/org/provider_name": "Pramaan Store 1",
          "tracking": false,
          "@ondc/org/category": "Standard Delivery",
          "@ondc/org/TAT": "PT15M",
          "state": {
            "descriptor": {
              "code": "Serviceable"
            }
          },
          "tags": [
            {
              "code": "order_details",
              "list": [
                {
                  "code": "weight_unit",
                  "value": "kilogram"
                },
                {
                  "code": "weight_value",
                  "value": "3.0"
                },
                {
                  "code": "dim_unit",
                  "value": "centimeter"
                },
                {
                  "code": "length",
                  "value": "1.0"
                },
                {
                  "code": "breadth",
                  "value": "1.0"
                },
                {
                  "code": "height",
                  "value": "1.0"
                }
              ]
            }
          ]
        }
      ],
      "items": [
        {
          "id": "id_1bai73_0_0",
          "quantity": {
            "count": 2
          },
          "location_id": "SSL1",
          "fulfillment_id": "4f71be37-57bb-439a-b803-e1133d6105d5"
        }
      ],
      "quote": {
        "price": {
          "currency": "INR",
          "value": "2765.00"
        },
        "breakup": [
          {
            "@ondc/org/item_id": "id_1bai73_0_0",
            "title": "Adidas Track Suit",
            "@ondc/org/item_quantity": {
              "count": 2
            },
            "@ondc/org/title_type": "item",
            "price": {
              "currency": "INR",
              "value": "2400.00"
            },
            "item": {
              "quantity": {
                "available": {
                  "count": "99"
                },
                "maximum": {
                  "count": "99"
                }
              },
              "price": {
                "currency": "INR",
                "value": "1200.00"
              }
            }
          },
          {
            "@ondc/org/item_id": "4f71be37-57bb-439a-b803-e1133d6105d5",
            "title": "Delivery charges",
            "@ondc/org/title_type": "delivery",
            "price": {
              "currency": "INR",
              "value": "40"
            }
          },
          {
            "@ondc/org/item_id": "4f71be37-57bb-439a-b803-e1133d6105d5",
            "title": "Tax",
            "@ondc/org/title_type": "tax",
            "price": {
              "currency": "INR",
              "value": "5"
            },
            "item": {
              "tags": [
                {
                  "code": "quote",
                  "list": [
                    {
                      "code": "type",
                      "value": "fulfillment"
                    },
                    {
                      "code": "subtype",
                      "value": "delivery"
                    }
                  ]
                }
              ]
            }
          },
          {
            "@ondc/org/item_id": "4f71be37-57bb-439a-b803-e1133d6105d5",
            "title": "Convenience Fee",
            "@ondc/org/title_type": "misc",
            "price": {
              "currency": "INR",
              "value": "40"
            },
            "item": {
              "tags": [
                {
                  "code": "quote",
                  "list": [
                    {
                      "code": "type",
                      "value": "item"
                    }
                  ]
                },
                {
                  "code": "np_fees",
                  "list": [
                    {
                      "code": "id",
                      "value": "1"
                    },
                    {
                      "code": "channel_margin_type",
                      "value": "percent"
                    },
                    {
                      "code": "channel_margin_value",
                      "value": "0.50"
                    }
                  ]
                }
              ]
            }
          },
          {
            "@ondc/org/item_id": "4f71be37-57bb-439a-b803-e1133d6105d5",
            "title": "Convenience Fee",
            "@ondc/org/title_type": "misc",
            "price": {
              "currency": "INR",
              "value": "40"
            },
            "item": {
              "tags": [
                {
                  "code": "quote",
                  "list": [
                    {
                      "code": "type",
                      "value": "item"
                    }
                  ]
                },
                {
                  "code": "np_fees",
                  "list": [
                    {
                      "code": "id",
                      "value": "2"
                    },
                    {
                      "code": "channel_margin_type",
                      "value": "percent"
                    },
                    {
                      "code": "channel_margin_value",
                      "value": "0.75"
                    }
                  ]
                }
              ]
            }
          },
          {
            "@ondc/org/item_id": "4f71be37-57bb-439a-b803-e1133d6105d5",
            "title": "Tax",
            "@ondc/org/title_type": "tax",
            "price": {
              "currency": "INR",
              "value": "5"
            },
            "item": {
              "tags": [
                {
                  "code": "quote",
                  "list": [
                    {
                      "code": "type",
                      "value": "item"
                    },
                    {
                      "code": "subtype",
                      "value": "misc"
                    }
                  ]
                },
                {
                  "code": "np_fees",
                  "list": [
                    {
                      "code": "id",
                      "value": "1"
                    }
                  ]
                }
              ]
            }
          },
          {
            "@ondc/org/item_id": "4f71be37-57bb-439a-b803-e1133d6105d5",
            "title": "Tax",
            "@ondc/org/title_type": "tax",
            "price": {
              "currency": "INR",
              "value": "5"
            },
            "item": {
              "tags": [
                {
                  "code": "quote",
                  "list": [
                    {
                      "code": "type",
                      "value": "item"
                    },
                    {
                      "code": "subtype",
                      "value": "misc"
                    }
                  ]
                },
                {
                  "code": "np_fees",
                  "list": [
                    {
                      "code": "id",
                      "value": "2"
                    }
                  ]
                }
              ]
            }
          },
          {
            "@ondc/org/item_id": "2490fae2-690e-4694-bedc-50aac1ed1d85",
            "title": "Delivery charges",
            "@ondc/org/title_type": "delivery",
            "price": {
              "currency": "INR",
              "value": "0"
            }
          },
          {
            "@ondc/org/item_id": "2490fae2-690e-4694-bedc-50aac1ed1d85",
            "title": "Packing charges",
            "@ondc/org/title_type": "packing",
            "price": {
              "currency": "INR",
              "value": "25"
            }
          },
          {
            "@ondc/org/item_id": "2490fae2-690e-4694-bedc-50aac1ed1d85",
            "title": "Tax",
            "@ondc/org/title_type": "tax",
            "price": {
              "currency": "INR",
              "value": "5"
            },
            "item": {
              "tags": [
                {
                  "code": "quote",
                  "list": [
                    {
                      "code": "type",
                      "value": "item"
                    },
                    {
                      "code": "subtype",
                      "value": "misc"
                    }
                  ]
                },
                {
                  "code": "np_fees",
                  "list": [
                    {
                      "code": "id",
                      "value": "1"
                    }
                  ]
                }
              ]
            }
          },
          {
            "@ondc/org/item_id": "2490fae2-690e-4694-bedc-50aac1ed1d85",
            "title": "Tax",
            "@ondc/org/title_type": "tax",
            "price": {
              "currency": "INR",
              "value": "5"
            },
            "item": {
              "tags": [
                {
                  "code": "quote",
                  "list": [
                    {
                      "code": "type",
                      "value": "item"
                    },
                    {
                      "code": "subtype",
                      "value": "misc"
                    }
                  ]
                },
                {
                  "code": "np_fees",
                  "list": [
                    {
                      "code": "id",
                      "value": "2"
                    }
                  ]
                }
              ]
            }
          },
          {
            "@ondc/org/item_id": "2490fae2-690e-4694-bedc-50aac1ed1d85",
            "title": "Convenience Fee",
            "@ondc/org/title_type": "misc",
            "price": {
              "currency": "INR",
              "value": "40"
            },
            "item": {
              "tags": [
                {
                  "code": "quote",
                  "list": [
                    {
                      "code": "type",
                      "value": "item"
                    }
                  ]
                },
                {
                  "code": "np_fees",
                  "list": [
                    {
                      "code": "id",
                      "value": "1"
                    },
                    {
                      "code": "channel_margin_type",
                      "value": "percent"
                    },
                    {
                      "code": "channel_margin_value",
                      "value": "0.50"
                    }
                  ]
                }
              ]
            }
          },
          {
            "@ondc/org/item_id": "2490fae2-690e-4694-bedc-50aac1ed1d85",
            "title": "Convenience Fee",
            "@ondc/org/title_type": "misc",
            "price": {
              "currency": "INR",
              "value": "40"
            },
            "item": {
              "tags": [
                {
                  "code": "quote",
                  "list": [
                    {
                      "code": "type",
                      "value": "item"
                    }
                  ]
                },
                {
                  "code": "np_fees",
                  "list": [
                    {
                      "code": "id",
                      "value": "2"
                    },
                    {
                      "code": "channel_margin_type",
                      "value": "percent"
                    },
                    {
                      "code": "channel_margin_value",
                      "value": "0.75"
                    }
                  ]
                }
              ]
            }
          },
          {
            "@ondc/org/item_id": "d0499d73-d43e-4957-b3a2-a3e306db0d1e",
            "title": "Delivery charges",
            "@ondc/org/title_type": "delivery",
            "price": {
              "currency": "INR",
              "value": "0"
            }
          },
          {
            "@ondc/org/item_id": "d0499d73-d43e-4957-b3a2-a3e306db0d1e",
            "title": "Packing charges",
            "@ondc/org/title_type": "packing",
            "price": {
              "currency": "INR",
              "value": "25"
            }
          },
          {
            "@ondc/org/item_id": "d0499d73-d43e-4957-b3a2-a3e306db0d1e",
            "title": "Tax",
            "@ondc/org/title_type": "tax",
            "price": {
              "currency": "INR",
              "value": "5"
            },
            "item": {
              "tags": [
                {
                  "code": "quote",
                  "list": [
                    {
                      "code": "type",
                      "value": "item"
                    },
                    {
                      "code": "subtype",
                      "value": "misc"
                    }
                  ]
                },
                {
                  "code": "np_fees",
                  "list": [
                    {
                      "code": "id",
                      "value": "1"
                    }
                  ]
                }
              ]
            }
          },
          {
            "@ondc/org/item_id": "d0499d73-d43e-4957-b3a2-a3e306db0d1e",
            "title": "Tax",
            "@ondc/org/title_type": "tax",
            "price": {
              "currency": "INR",
              "value": "5"
            },
            "item": {
              "tags": [
                {
                  "code": "quote",
                  "list": [
                    {
                      "code": "type",
                      "value": "item"
                    },
                    {
                      "code": "subtype",
                      "value": "misc"
                    }
                  ]
                },
                {
                  "code": "np_fees",
                  "list": [
                    {
                      "code": "id",
                      "value": "2"
                    }
                  ]
                }
              ]
            }
          },
          {
            "@ondc/org/item_id": "d0499d73-d43e-4957-b3a2-a3e306db0d1e",
            "title": "Convenience Fee",
            "@ondc/org/title_type": "misc",
            "price": {
              "currency": "INR",
              "value": "40"
            },
            "item": {
              "tags": [
                {
                  "code": "quote",
                  "list": [
                    {
                      "code": "type",
                      "value": "item"
                    }
                  ]
                },
                {
                  "code": "np_fees",
                  "list": [
                    {
                      "code": "id",
                      "value": "1"
                    },
                    {
                      "code": "channel_margin_type",
                      "value": "percent"
                    },
                    {
                      "code": "channel_margin_value",
                      "value": "0.50"
                    }
                  ]
                }
              ]
            }
          },
          {
            "@ondc/org/item_id": "d0499d73-d43e-4957-b3a2-a3e306db0d1e",
            "title": "Convenience Fee",
            "@ondc/org/title_type": "misc",
            "price": {
              "currency": "INR",
              "value": "40"
            },
            "item": {
              "tags": [
                {
                  "code": "quote",
                  "list": [
                    {
                      "code": "type",
                      "value": "item"
                    }
                  ]
                },
                {
                  "code": "np_fees",
                  "list": [
                    {
                      "code": "id",
                      "value": "2"
                    },
                    {
                      "code": "channel_margin_type",
                      "value": "percent"
                    },
                    {
                      "code": "channel_margin_value",
                      "value": "0.75"
                    }
                  ]
                }
              ]
            }
          }
        ],
        "ttl": "PT6H"
      },
      "provider": {
        "id": "pramaan_provider_1",
        "locations": [
          {
            "id": "SSL1"
          }
        ]
      }
    }
  }
}