{
    "context": {
      "domain": "ONDC:RET11",
      "country": "IND",
      "city": "std:0124",
      "core_version": "1.2.5",
      "action": "on_track",
      "transaction_id": "62579764-4dd5-4c06-92a4-ef9a0aa5a76d",
      "message_id": "4354d603-e970-4729-baba-f7b6496ea610",
      "timestamp": "2025-07-28T04:41:44.812Z",
      "bap_uri": "https://ondc.sequelstring.com/buyer/protocol",
      "bap_id": "ondc.sequelstring.com/buyer/protocol",
      "bpp_id": "ondc.sequelstring.com/seller/protocol",
      "bpp_uri": "https://ondc.sequelstring.com/seller/protocol"
    },
    "message": {
      "tracking": {
        "id": "c806d3d6-170d-4427-90c9-dfbb6d27c1e2",
        "url": "http://sequelstring-lsp-ondc.com/track",
        "status": "active"
      }
    }
}